galadriel/__init__.py
galadriel/agent.py
galadriel/cli.py
galadriel/clients/__init__.py
galadriel/clients/chatui_client.py
galadriel/clients/cron.py
galadriel/clients/discord_client.py
galadriel/clients/gradio_client.py
galadriel/clients/simple_message_client.py
galadriel/clients/telegram_client.py
galadriel/clients/terminal_client.py
galadriel/clients/twitter_mention_client.py
galadriel/clients/twitter_post_client.py
galadriel/connectors/llm.py
galadriel/connectors/perplexity.py
galadriel/connectors/twitter.py
galadriel/docker/.dockerignore
galadriel/docker/Dockerfile
galadriel/docker/galadriel_base_image/.gitignore
galadriel/docker/galadriel_base_image/Dockerfile
galadriel/docker/galadriel_base_image/enclave_services/agent_manager.py
galadriel/docker/galadriel_base_image/enclave_services/attestation_manager.py
galadriel/docker/galadriel_base_image/enclave_services/dns_forwarder.py
galadriel/docker/galadriel_base_image/enclave_services/enclave_server.py
galadriel/docker/galadriel_base_image/enclave_services/env_var_service.py
galadriel/docker/galadriel_base_image/enclave_services/inbound_chat_forwarder.py
galadriel/docker/galadriel_base_image/enclave_services/libnsm.so
galadriel/docker/galadriel_base_image/enclave_services/main.py
galadriel/docker/galadriel_base_image/enclave_services/nsm_util.py
galadriel/docker/galadriel_base_image/enclave_services/requirements.txt
galadriel/docker/galadriel_base_image/enclave_services/traffic_forwarder.py
galadriel/docker/galadriel_base_image/run.sh
galadriel/docker/galadriel_base_image/setup_forwarding.sh
galadriel/docker/logrotate_logs
galadriel/docker-compose.yml
galadriel/domain/extract_step_logs.py
galadriel/domain/logs_exporter.py
galadriel/domain/prompts/format_prompt.py
galadriel/domain/validate_solana_payment.py
galadriel/entities.py
galadriel/errors.py
galadriel/logging_utils.py
galadriel/memory/__init__.py
galadriel/memory/memory_store.py
galadriel/proof/__init__.py
galadriel/proof/prover.py
galadriel/serializable.py
galadriel-0.0.16.dist-info/METADATA
galadriel-0.0.16.dist-info/WHEEL
galadriel-0.0.16.dist-info/entry_points.txt
galadriel-0.0.16.dist-info/RECORD
